<?xml version="1.0" encoding="UTF-8" standalone="yes"?><template><description></description><name>HandleNifiReports</name><snippet><connections><id>27a178e3-3e6a-45dc-9e31-f1b5b9082b0b</id><parentGroupId>b8cbae40-4019-4c69-b185-df812e88e5be</parentGroupId><backPressureDataSizeThreshold>0 MB</backPressureDataSizeThreshold><backPressureObjectThreshold>0</backPressureObjectThreshold><destination><groupId>b8cbae40-4019-4c69-b185-df812e88e5be</groupId><id>e58e0b99-96a4-466c-8b5d-b113c45e9ee4</id><type>PROCESSOR</type></destination><flowFileExpiration>0 sec</flowFileExpiration><labelIndex>1</labelIndex><name></name><selectedRelationships>split</selectedRelationships><source><groupId>b8cbae40-4019-4c69-b185-df812e88e5be</groupId><id>63a5237f-f25b-407c-a677-4207c7959099</id><type>PROCESSOR</type></source><zIndex>0</zIndex></connections><connections><id>af3f6cd7-3d72-4c6d-a00e-773f7ec2657f</id><parentGroupId>b8cbae40-4019-4c69-b185-df812e88e5be</parentGroupId><backPressureDataSizeThreshold>0 MB</backPressureDataSizeThreshold><backPressureObjectThreshold>0</backPressureObjectThreshold><destination><groupId>b8cbae40-4019-4c69-b185-df812e88e5be</groupId><id>94b8eab5-ee3c-470d-845b-cf5c70840bb7</id><type>PROCESSOR</type></destination><flowFileExpiration>0 sec</flowFileExpiration><labelIndex>1</labelIndex><name></name><selectedRelationships>matched</selectedRelationships><source><groupId>b8cbae40-4019-4c69-b185-df812e88e5be</groupId><id>e58e0b99-96a4-466c-8b5d-b113c45e9ee4</id><type>PROCESSOR</type></source><zIndex>0</zIndex></connections><connections><id>3eab570c-c088-4c8e-85f2-31f137d56694</id><parentGroupId>b8cbae40-4019-4c69-b185-df812e88e5be</parentGroupId><backPressureDataSizeThreshold>0 MB</backPressureDataSizeThreshold><backPressureObjectThreshold>0</backPressureObjectThreshold><destination><groupId>b8cbae40-4019-4c69-b185-df812e88e5be</groupId><id>c5a94d4c-c2bb-40de-a827-244e74528fe4</id><type>PROCESSOR</type></destination><flowFileExpiration>0 sec</flowFileExpiration><labelIndex>1</labelIndex><name></name><selectedRelationships>success</selectedRelationships><source><groupId>b8cbae40-4019-4c69-b185-df812e88e5be</groupId><id>d2c79bcd-8566-456d-919b-0a60d1412bf9</id><type>PROCESSOR</type></source><zIndex>0</zIndex></connections><connections><id>7aa45385-1a84-4acb-b246-c8c39d719462</id><parentGroupId>b8cbae40-4019-4c69-b185-df812e88e5be</parentGroupId><backPressureDataSizeThreshold>0 MB</backPressureDataSizeThreshold><backPressureObjectThreshold>0</backPressureObjectThreshold><destination><groupId>b8cbae40-4019-4c69-b185-df812e88e5be</groupId><id>ae0e311a-95aa-4e2e-bbff-c338653e57c3</id><type>PROCESSOR</type></destination><flowFileExpiration>0 sec</flowFileExpiration><labelIndex>1</labelIndex><name></name><selectedRelationships>success</selectedRelationships><source><groupId>b8cbae40-4019-4c69-b185-df812e88e5be</groupId><id>94b8eab5-ee3c-470d-845b-cf5c70840bb7</id><type>PROCESSOR</type></source><zIndex>0</zIndex></connections><connections><id>67410f20-94d8-4563-b8fb-2bce631df756</id><parentGroupId>b8cbae40-4019-4c69-b185-df812e88e5be</parentGroupId><backPressureDataSizeThreshold>0 MB</backPressureDataSizeThreshold><backPressureObjectThreshold>0</backPressureObjectThreshold><destination><groupId>b8cbae40-4019-4c69-b185-df812e88e5be</groupId><id>63a5237f-f25b-407c-a677-4207c7959099</id><type>PROCESSOR</type></destination><flowFileExpiration>0 sec</flowFileExpiration><labelIndex>1</labelIndex><name></name><selectedRelationships>success</selectedRelationships><source><groupId>b8cbae40-4019-4c69-b185-df812e88e5be</groupId><id>d2c79bcd-8566-456d-919b-0a60d1412bf9</id><type>PROCESSOR</type></source><zIndex>0</zIndex></connections><controllerServices><id>bc09bb31-fbf8-44ef-8115-0351fe2e4e37</id><descriptors><entry><key>Maximum Outstanding Requests</key><value><defaultValue>5000</defaultValue><description>The maximum number of HTTP requests that can be outstanding at any one time. Any attempt to register an additional HTTP Request will cause an error</description><displayName>Maximum Outstanding Requests</displayName><dynamic>false</dynamic><name>Maximum Outstanding Requests</name><required>true</required><sensitive>false</sensitive><supportsEl>false</supportsEl></value></entry><entry><key>Request Expiration</key><value><defaultValue>1 min</defaultValue><description>Specifies how long an HTTP Request should be left unanswered before being evicted from the cache and being responded to with a Service Unavailable status code</description><displayName>Request Expiration</displayName><dynamic>false</dynamic><name>Request Expiration</name><required>true</required><sensitive>false</sensitive><supportsEl>false</supportsEl></value></entry></descriptors><name>StandardHttpContextMap</name><properties><entry><key>Maximum Outstanding Requests</key></entry><entry><key>Request Expiration</key></entry></properties><referencingComponents><activeThreadCount>0</activeThreadCount><descriptors><entry><key>Listening Port</key><value><defaultValue>80</defaultValue><description>The Port to listen on for incoming HTTP requests</description><displayName>Listening Port</displayName><dynamic>false</dynamic><name>Listening Port</name><required>true</required><sensitive>false</sensitive><supportsEl>false</supportsEl></value></entry><entry><key>Hostname</key><value><description>The Hostname to bind to. If not specified, will bind to all hosts</description><displayName>Hostname</displayName><dynamic>false</dynamic><name>Hostname</name><required>false</required><sensitive>false</sensitive><supportsEl>false</supportsEl></value></entry><entry><key>SSL Context Service</key><value><description>The SSL Context Service to use in order to secure the server. If specified, the server will accept only HTTPS requests; otherwise, the server will accept only HTTP requests</description><displayName>SSL Context Service</displayName><dynamic>false</dynamic><identifiesControllerService>org.apache.nifi.ssl.SSLContextService</identifiesControllerService><name>SSL Context Service</name><required>false</required><sensitive>false</sensitive><supportsEl>false</supportsEl></value></entry><entry><key>HTTP Context Map</key><value><allowableValues><displayName>StandardHttpContextMap</displayName><value>bc09bb31-fbf8-44ef-8115-0351fe2e4e37</value></allowableValues><description>The HTTP Context Map Controller Service to use for caching the HTTP Request Information</description><displayName>HTTP Context Map</displayName><dynamic>false</dynamic><identifiesControllerService>org.apache.nifi.http.HttpContextMap</identifiesControllerService><name>HTTP Context Map</name><required>true</required><sensitive>false</sensitive><supportsEl>false</supportsEl></value></entry><entry><key>Allowed Paths</key><value><description>A Regular Expression that specifies the valid HTTP Paths that are allowed in the incoming URL Requests. If this value is specified and the path of the HTTP Requests does not match this Regular Expression, the Processor will respond with a 404: NotFound</description><displayName>Allowed Paths</displayName><dynamic>false</dynamic><name>Allowed Paths</name><required>false</required><sensitive>false</sensitive><supportsEl>false</supportsEl></value></entry><entry><key>Default URL Character Set</key><value><defaultValue>UTF-8</defaultValue><description>The character set to use for decoding URL parameters if the HTTP Request does not supply one</description><displayName>Default URL Character Set</displayName><dynamic>false</dynamic><name>Default URL Character Set</name><required>true</required><sensitive>false</sensitive><supportsEl>false</supportsEl></value></entry><entry><key>Allow GET</key><value><allowableValues><displayName>true</displayName><value>true</value></allowableValues><allowableValues><displayName>false</displayName><value>false</value></allowableValues><defaultValue>true</defaultValue><description>Allow HTTP GET Method</description><displayName>Allow GET</displayName><dynamic>false</dynamic><name>Allow GET</name><required>true</required><sensitive>false</sensitive><supportsEl>false</supportsEl></value></entry><entry><key>Allow POST</key><value><allowableValues><displayName>true</displayName><value>true</value></allowableValues><allowableValues><displayName>false</displayName><value>false</value></allowableValues><defaultValue>true</defaultValue><description>Allow HTTP POST Method</description><displayName>Allow POST</displayName><dynamic>false</dynamic><name>Allow POST</name><required>true</required><sensitive>false</sensitive><supportsEl>false</supportsEl></value></entry><entry><key>Allow PUT</key><value><allowableValues><displayName>true</displayName><value>true</value></allowableValues><allowableValues><displayName>false</displayName><value>false</value></allowableValues><defaultValue>true</defaultValue><description>Allow HTTP PUT Method</description><displayName>Allow PUT</displayName><dynamic>false</dynamic><name>Allow PUT</name><required>true</required><sensitive>false</sensitive><supportsEl>false</supportsEl></value></entry><entry><key>Allow DELETE</key><value><allowableValues><displayName>true</displayName><value>true</value></allowableValues><allowableValues><displayName>false</displayName><value>false</value></allowableValues><defaultValue>true</defaultValue><description>Allow HTTP DELETE Method</description><displayName>Allow DELETE</displayName><dynamic>false</dynamic><name>Allow DELETE</name><required>true</required><sensitive>false</sensitive><supportsEl>false</supportsEl></value></entry><entry><key>Allow HEAD</key><value><allowableValues><displayName>true</displayName><value>true</value></allowableValues><allowableValues><displayName>false</displayName><value>false</value></allowableValues><defaultValue>false</defaultValue><description>Allow HTTP HEAD Method</description><displayName>Allow HEAD</displayName><dynamic>false</dynamic><name>Allow HEAD</name><required>true</required><sensitive>false</sensitive><supportsEl>false</supportsEl></value></entry><entry><key>Allow OPTIONS</key><value><allowableValues><displayName>true</displayName><value>true</value></allowableValues><allowableValues><displayName>false</displayName><value>false</value></allowableValues><defaultValue>false</defaultValue><description>Allow HTTP OPTIONS Method</description><displayName>Allow OPTIONS</displayName><dynamic>false</dynamic><name>Allow OPTIONS</name><required>true</required><sensitive>false</sensitive><supportsEl>false</supportsEl></value></entry><entry><key>Additional HTTP Methods</key><value><description>A comma-separated list of non-standard HTTP Methods that should be allowed</description><displayName>Additional HTTP Methods</displayName><dynamic>false</dynamic><name>Additional HTTP Methods</name><required>false</required><sensitive>false</sensitive><supportsEl>false</supportsEl></value></entry><entry><key>Client Authentication</key><value><allowableValues><description>Processor will not authenticate clients. Anyone can communicate with this Processor anonymously</description><displayName>No Authentication</displayName><value>No Authentication</value></allowableValues><allowableValues><description>Processor will try to verify the client but if unable to verify will allow the client to communicate anonymously</description><displayName>Want Authentication</displayName><value>Want Authentication</value></allowableValues><allowableValues><description>Processor will reject communications from any client unless the client provides a certificate that is trusted by the TrustStorespecified in the SSL Context Service</description><displayName>Need Authentication</displayName><value>Need Authentication</value></allowableValues><defaultValue>No Authentication</defaultValue><description>Specifies whether or not the Processor should authenticate clients. This value is ignored if the &lt;SSL Context Service&gt; Property is not specified or the SSL Context provided uses only a KeyStore and not a TrustStore.</description><displayName>Client Authentication</displayName><dynamic>false</dynamic><name>Client Authentication</name><required>true</required><sensitive>false</sensitive><supportsEl>false</supportsEl></value></entry></descriptors><groupId>b8cbae40-4019-4c69-b185-df812e88e5be</groupId><id>d2c79bcd-8566-456d-919b-0a60d1412bf9</id><name>Incoming Ambari report</name><properties><entry><key>Listening Port</key><value>8680</value></entry><entry><key>Hostname</key><value>localhost</value></entry><entry><key>SSL Context Service</key></entry><entry><key>HTTP Context Map</key><value>bc09bb31-fbf8-44ef-8115-0351fe2e4e37</value></entry><entry><key>Allowed Paths</key></entry><entry><key>Default URL Character Set</key></entry><entry><key>Allow GET</key></entry><entry><key>Allow POST</key></entry><entry><key>Allow PUT</key></entry><entry><key>Allow DELETE</key></entry><entry><key>Allow HEAD</key></entry><entry><key>Allow OPTIONS</key></entry><entry><key>Additional HTTP Methods</key></entry><entry><key>Client Authentication</key></entry></properties><referenceType>Processor</referenceType><state>STOPPED</state><type>org.apache.nifi.processors.standard.HandleHttpRequest</type></referencingComponents><referencingComponents><activeThreadCount>0</activeThreadCount><descriptors><entry><key>HTTP Status Code</key><value><description>The HTTP Status Code to use when responding to the HTTP Request. See Section 10 of RFC 2616 for more information.</description><displayName>HTTP Status Code</displayName><dynamic>false</dynamic><name>HTTP Status Code</name><required>true</required><sensitive>false</sensitive><supportsEl>true</supportsEl></value></entry><entry><key>HTTP Context Map</key><value><allowableValues><displayName>StandardHttpContextMap</displayName><value>bc09bb31-fbf8-44ef-8115-0351fe2e4e37</value></allowableValues><description>The HTTP Context Map Controller Service to use for caching the HTTP Request Information</description><displayName>HTTP Context Map</displayName><dynamic>false</dynamic><identifiesControllerService>org.apache.nifi.http.HttpContextMap</identifiesControllerService><name>HTTP Context Map</name><required>true</required><sensitive>false</sensitive><supportsEl>false</supportsEl></value></entry></descriptors><groupId>b8cbae40-4019-4c69-b185-df812e88e5be</groupId><id>c5a94d4c-c2bb-40de-a827-244e74528fe4</id><name>Respond OK</name><properties><entry><key>HTTP Status Code</key><value>200</value></entry><entry><key>HTTP Context Map</key><value>bc09bb31-fbf8-44ef-8115-0351fe2e4e37</value></entry></properties><referenceType>Processor</referenceType><state>STOPPED</state><type>org.apache.nifi.processors.standard.HandleHttpResponse</type></referencingComponents><state>ENABLED</state><type>org.apache.nifi.http.StandardHttpContextMap</type></controllerServices><processors><id>63a5237f-f25b-407c-a677-4207c7959099</id><parentGroupId>b8cbae40-4019-4c69-b185-df812e88e5be</parentGroupId><position><x>-154.91758313489458</x><y>310.8938600052136</y></position><config><bulletinLevel>WARN</bulletinLevel><comments></comments><concurrentlySchedulableTaskCount>1</concurrentlySchedulableTaskCount><defaultConcurrentTasks><entry><key>TIMER_DRIVEN</key><value>1</value></entry><entry><key>EVENT_DRIVEN</key><value>0</value></entry><entry><key>CRON_DRIVEN</key><value>1</value></entry></defaultConcurrentTasks><defaultSchedulingPeriod><entry><key>TIMER_DRIVEN</key><value>0 sec</value></entry><entry><key>CRON_DRIVEN</key><value>* * * * * ?</value></entry></defaultSchedulingPeriod><descriptors><entry><key>JsonPath Expression</key><value><description>A JsonPath expression that indicates the array element to split into JSON/scalar fragments.</description><displayName>JsonPath Expression</displayName><dynamic>false</dynamic><name>JsonPath Expression</name><required>true</required><sensitive>false</sensitive><supportsEl>false</supportsEl></value></entry><entry><key>Null Value Representation</key><value><allowableValues><displayName>empty string</displayName><value>empty string</value></allowableValues><allowableValues><displayName>the string 'null'</displayName><value>the string 'null'</value></allowableValues><defaultValue>empty string</defaultValue><description>Indicates the desired representation of JSON Path expressions resulting in a null value.</description><displayName>Null Value Representation</displayName><dynamic>false</dynamic><name>Null Value Representation</name><required>true</required><sensitive>false</sensitive><supportsEl>false</supportsEl></value></entry></descriptors><lossTolerant>false</lossTolerant><penaltyDuration>30 sec</penaltyDuration><properties><entry><key>JsonPath Expression</key><value>$.metrics</value></entry><entry><key>Null Value Representation</key></entry></properties><runDurationMillis>0</runDurationMillis><schedulingPeriod>0 sec</schedulingPeriod><schedulingStrategy>TIMER_DRIVEN</schedulingStrategy><yieldDuration>1 sec</yieldDuration></config><name>Split Metrics into FlowFiles</name><relationships><autoTerminate>true</autoTerminate><description>If a FlowFile fails processing for any reason (for example, the FlowFile is not valid JSON or the specified path does not exist), it will be routed to this relationship</description><name>failure</name></relationships><relationships><autoTerminate>true</autoTerminate><description>The original FlowFile that was split into segments. If the FlowFile fails processing, nothing will be sent to this relationship</description><name>original</name></relationships><relationships><autoTerminate>false</autoTerminate><description>All segments of the original FlowFile will be routed to this relationship</description><name>split</name></relationships><state>STOPPED</state><style/><supportsEventDriven>true</supportsEventDriven><supportsParallelProcessing>true</supportsParallelProcessing><type>org.apache.nifi.processors.standard.SplitJson</type></processors><processors><id>ae0e311a-95aa-4e2e-bbff-c338653e57c3</id><parentGroupId>b8cbae40-4019-4c69-b185-df812e88e5be</parentGroupId><position><x>390.366136375585</x><y>638.5290248050975</y></position><config><bulletinLevel>WARN</bulletinLevel><comments></comments><concurrentlySchedulableTaskCount>1</concurrentlySchedulableTaskCount><defaultConcurrentTasks><entry><key>TIMER_DRIVEN</key><value>1</value></entry><entry><key>EVENT_DRIVEN</key><value>0</value></entry><entry><key>CRON_DRIVEN</key><value>1</value></entry></defaultConcurrentTasks><defaultSchedulingPeriod><entry><key>TIMER_DRIVEN</key><value>0 sec</value></entry><entry><key>CRON_DRIVEN</key><value>* * * * * ?</value></entry></defaultSchedulingPeriod><descriptors><entry><key>Log Level</key><value><allowableValues><displayName>trace</displayName><value>trace</value></allowableValues><allowableValues><displayName>debug</displayName><value>debug</value></allowableValues><allowableValues><displayName>info</displayName><value>info</value></allowableValues><allowableValues><displayName>warn</displayName><value>warn</value></allowableValues><allowableValues><displayName>error</displayName><value>error</value></allowableValues><defaultValue>info</defaultValue><description>The Log Level to use when logging the Attributes</description><displayName>Log Level</displayName><dynamic>false</dynamic><name>Log Level</name><required>true</required><sensitive>false</sensitive><supportsEl>false</supportsEl></value></entry><entry><key>Log Payload</key><value><allowableValues><displayName>true</displayName><value>true</value></allowableValues><allowableValues><displayName>false</displayName><value>false</value></allowableValues><defaultValue>false</defaultValue><description>If true, the FlowFile's payload will be logged, in addition to its attributes; otherwise, just the Attributes will be logged.</description><displayName>Log Payload</displayName><dynamic>false</dynamic><name>Log Payload</name><required>true</required><sensitive>false</sensitive><supportsEl>false</supportsEl></value></entry><entry><key>Attributes to Log</key><value><description>A comma-separated list of Attributes to Log. If not specified, all attributes will be logged.</description><displayName>Attributes to Log</displayName><dynamic>false</dynamic><name>Attributes to Log</name><required>false</required><sensitive>false</sensitive><supportsEl>false</supportsEl></value></entry><entry><key>Attributes to Ignore</key><value><description>A comma-separated list of Attributes to ignore. If not specified, no attributes will be ignored.</description><displayName>Attributes to Ignore</displayName><dynamic>false</dynamic><name>Attributes to Ignore</name><required>false</required><sensitive>false</sensitive><supportsEl>false</supportsEl></value></entry><entry><key>Log prefix</key><value><description>Log prefix appended to the log lines. It helps to distinguish the output of multiple LogAttribute processors.</description><displayName>Log prefix</displayName><dynamic>false</dynamic><name>Log prefix</name><required>false</required><sensitive>false</sensitive><supportsEl>true</supportsEl></value></entry></descriptors><lossTolerant>false</lossTolerant><penaltyDuration>30 sec</penaltyDuration><properties><entry><key>Log Level</key></entry><entry><key>Log Payload</key></entry><entry><key>Attributes to Log</key><value>metric.name,metric.hostname,metric.timestamp,metric.value</value></entry><entry><key>Attributes to Ignore</key></entry><entry><key>Log prefix</key></entry></properties><runDurationMillis>0</runDurationMillis><schedulingPeriod>0 sec</schedulingPeriod><schedulingStrategy>TIMER_DRIVEN</schedulingStrategy><yieldDuration>1 sec</yieldDuration></config><name>Log metric attributes</name><relationships><autoTerminate>true</autoTerminate><description>All FlowFiles are routed to this relationship</description><name>success</name></relationships><state>STOPPED</state><style/><supportsEventDriven>true</supportsEventDriven><supportsParallelProcessing>true</supportsParallelProcessing><type>org.apache.nifi.processors.standard.LogAttribute</type></processors><processors><id>94b8eab5-ee3c-470d-845b-cf5c70840bb7</id><parentGroupId>b8cbae40-4019-4c69-b185-df812e88e5be</parentGroupId><position><x>-147.16424642685274</x><y>638.4473839428657</y></position><config><bulletinLevel>WARN</bulletinLevel><comments></comments><concurrentlySchedulableTaskCount>1</concurrentlySchedulableTaskCount><defaultConcurrentTasks><entry><key>TIMER_DRIVEN</key><value>1</value></entry><entry><key>EVENT_DRIVEN</key><value>0</value></entry><entry><key>CRON_DRIVEN</key><value>1</value></entry></defaultConcurrentTasks><defaultSchedulingPeriod><entry><key>TIMER_DRIVEN</key><value>0 sec</value></entry><entry><key>CRON_DRIVEN</key><value>* * * * * ?</value></entry></defaultSchedulingPeriod><descriptors><entry><key>Delete Attributes Expression</key><value><description>Regular expression for attributes to be deleted from flowfiles.</description><displayName>Delete Attributes Expression</displayName><dynamic>false</dynamic><name>Delete Attributes Expression</name><required>false</required><sensitive>false</sensitive><supportsEl>true</supportsEl></value></entry><entry><key>metric.value</key><value><description></description><displayName>metric.value</displayName><dynamic>true</dynamic><name>metric.value</name><required>false</required><sensitive>false</sensitive><supportsEl>true</supportsEl></value></entry></descriptors><lossTolerant>false</lossTolerant><penaltyDuration>30 sec</penaltyDuration><properties><entry><key>Delete Attributes Expression</key></entry><entry><key>metric.value</key><value>${metric.value:substring( 2,${metric.value:length():minus(2)} )}</value></entry></properties><runDurationMillis>0</runDurationMillis><schedulingPeriod>0 sec</schedulingPeriod><schedulingStrategy>TIMER_DRIVEN</schedulingStrategy><yieldDuration>1 sec</yieldDuration></config><name>Get the metric's value</name><relationships><autoTerminate>false</autoTerminate><description>All FlowFiles are routed to this relationship</description><name>success</name></relationships><state>STOPPED</state><style/><supportsEventDriven>true</supportsEventDriven><supportsParallelProcessing>true</supportsParallelProcessing><type>org.apache.nifi.processors.attributes.UpdateAttribute</type></processors><processors><id>e58e0b99-96a4-466c-8b5d-b113c45e9ee4</id><parentGroupId>b8cbae40-4019-4c69-b185-df812e88e5be</parentGroupId><position><x>-151.6933427238622</x><y>482.85369433764663</y></position><config><bulletinLevel>WARN</bulletinLevel><comments></comments><concurrentlySchedulableTaskCount>1</concurrentlySchedulableTaskCount><defaultConcurrentTasks><entry><key>TIMER_DRIVEN</key><value>1</value></entry><entry><key>EVENT_DRIVEN</key><value>0</value></entry><entry><key>CRON_DRIVEN</key><value>1</value></entry></defaultConcurrentTasks><defaultSchedulingPeriod><entry><key>TIMER_DRIVEN</key><value>0 sec</value></entry><entry><key>CRON_DRIVEN</key><value>* * * * * ?</value></entry></defaultSchedulingPeriod><descriptors><entry><key>Destination</key><value><allowableValues><displayName>flowfile-content</displayName><value>flowfile-content</value></allowableValues><allowableValues><displayName>flowfile-attribute</displayName><value>flowfile-attribute</value></allowableValues><defaultValue>flowfile-content</defaultValue><description>Indicates whether the results of the JsonPath evaluation are written to the FlowFile content or a FlowFile attribute; if using attribute, must specify the Attribute Name property. If set to flowfile-content, only one JsonPath may be specified, and the property name is ignored.</description><displayName>Destination</displayName><dynamic>false</dynamic><name>Destination</name><required>true</required><sensitive>false</sensitive><supportsEl>false</supportsEl></value></entry><entry><key>Return Type</key><value><allowableValues><displayName>auto-detect</displayName><value>auto-detect</value></allowableValues><allowableValues><displayName>json</displayName><value>json</value></allowableValues><allowableValues><displayName>scalar</displayName><value>scalar</value></allowableValues><defaultValue>auto-detect</defaultValue><description>Indicates the desired return type of the JSON Path expressions.  Selecting 'auto-detect' will set the return type to 'json' for a Destination of 'flowfile-content', and 'scalar' for a Destination of 'flowfile-attribute'.</description><displayName>Return Type</displayName><dynamic>false</dynamic><name>Return Type</name><required>true</required><sensitive>false</sensitive><supportsEl>false</supportsEl></value></entry><entry><key>Path Not Found Behavior</key><value><allowableValues><displayName>warn</displayName><value>warn</value></allowableValues><allowableValues><displayName>ignore</displayName><value>ignore</value></allowableValues><defaultValue>ignore</defaultValue><description>Indicates how to handle missing JSON path expressions when destination is set to 'flowfile-attribute'. Selecting 'warn' will generate a warning when a JSON path expression is not found.</description><displayName>Path Not Found Behavior</displayName><dynamic>false</dynamic><name>Path Not Found Behavior</name><required>true</required><sensitive>false</sensitive><supportsEl>false</supportsEl></value></entry><entry><key>Null Value Representation</key><value><allowableValues><displayName>empty string</displayName><value>empty string</value></allowableValues><allowableValues><displayName>the string 'null'</displayName><value>the string 'null'</value></allowableValues><defaultValue>empty string</defaultValue><description>Indicates the desired representation of JSON Path expressions resulting in a null value.</description><displayName>Null Value Representation</displayName><dynamic>false</dynamic><name>Null Value Representation</name><required>true</required><sensitive>false</sensitive><supportsEl>false</supportsEl></value></entry><entry><key>metric.hostname</key><value><description></description><displayName>metric.hostname</displayName><dynamic>true</dynamic><name>metric.hostname</name><required>false</required><sensitive>false</sensitive><supportsEl>false</supportsEl></value></entry><entry><key>metric.name</key><value><description></description><displayName>metric.name</displayName><dynamic>true</dynamic><name>metric.name</name><required>false</required><sensitive>false</sensitive><supportsEl>false</supportsEl></value></entry><entry><key>metric.timestamp</key><value><description></description><displayName>metric.timestamp</displayName><dynamic>true</dynamic><name>metric.timestamp</name><required>false</required><sensitive>false</sensitive><supportsEl>false</supportsEl></value></entry><entry><key>metric.value</key><value><description></description><displayName>metric.value</displayName><dynamic>true</dynamic><name>metric.value</name><required>false</required><sensitive>false</sensitive><supportsEl>false</supportsEl></value></entry></descriptors><lossTolerant>false</lossTolerant><penaltyDuration>30 sec</penaltyDuration><properties><entry><key>Destination</key><value>flowfile-attribute</value></entry><entry><key>Return Type</key><value>json</value></entry><entry><key>Path Not Found Behavior</key><value>warn</value></entry><entry><key>Null Value Representation</key></entry><entry><key>metric.hostname</key><value>$.hostname</value></entry><entry><key>metric.name</key><value>$.metricname</value></entry><entry><key>metric.timestamp</key><value>$.timestamp</value></entry><entry><key>metric.value</key><value>$.metrics.*</value></entry></properties><runDurationMillis>0</runDurationMillis><schedulingPeriod>0 sec</schedulingPeriod><schedulingStrategy>TIMER_DRIVEN</schedulingStrategy><yieldDuration>1 sec</yieldDuration></config><name>Get Metric info as attributes</name><relationships><autoTerminate>true</autoTerminate><description>FlowFiles are routed to this relationship when the JsonPath cannot be evaluated against the content of the FlowFile; for instance, if the FlowFile is not valid JSON</description><name>failure</name></relationships><relationships><autoTerminate>false</autoTerminate><description>FlowFiles are routed to this relationship when the JsonPath is successfully evaluated and the FlowFile is modified as a result</description><name>matched</name></relationships><relationships><autoTerminate>true</autoTerminate><description>FlowFiles are routed to this relationship when the JsonPath does not match the content of the FlowFile and the Destination is set to flowfile-content</description><name>unmatched</name></relationships><state>STOPPED</state><style/><supportsEventDriven>true</supportsEventDriven><supportsParallelProcessing>true</supportsParallelProcessing><type>org.apache.nifi.processors.standard.EvaluateJsonPath</type></processors><processors><id>d2c79bcd-8566-456d-919b-0a60d1412bf9</id><parentGroupId>b8cbae40-4019-4c69-b185-df812e88e5be</parentGroupId><position><x>-157.06709063937382</x><y>106.6915002126737</y></position><config><bulletinLevel>WARN</bulletinLevel><comments></comments><concurrentlySchedulableTaskCount>1</concurrentlySchedulableTaskCount><defaultConcurrentTasks><entry><key>TIMER_DRIVEN</key><value>1</value></entry><entry><key>EVENT_DRIVEN</key><value>0</value></entry><entry><key>CRON_DRIVEN</key><value>1</value></entry></defaultConcurrentTasks><defaultSchedulingPeriod><entry><key>TIMER_DRIVEN</key><value>0 sec</value></entry><entry><key>CRON_DRIVEN</key><value>* * * * * ?</value></entry></defaultSchedulingPeriod><descriptors><entry><key>Listening Port</key><value><defaultValue>80</defaultValue><description>The Port to listen on for incoming HTTP requests</description><displayName>Listening Port</displayName><dynamic>false</dynamic><name>Listening Port</name><required>true</required><sensitive>false</sensitive><supportsEl>false</supportsEl></value></entry><entry><key>Hostname</key><value><description>The Hostname to bind to. If not specified, will bind to all hosts</description><displayName>Hostname</displayName><dynamic>false</dynamic><name>Hostname</name><required>false</required><sensitive>false</sensitive><supportsEl>false</supportsEl></value></entry><entry><key>SSL Context Service</key><value><description>The SSL Context Service to use in order to secure the server. If specified, the server will accept only HTTPS requests; otherwise, the server will accept only HTTP requests</description><displayName>SSL Context Service</displayName><dynamic>false</dynamic><identifiesControllerService>org.apache.nifi.ssl.SSLContextService</identifiesControllerService><name>SSL Context Service</name><required>false</required><sensitive>false</sensitive><supportsEl>false</supportsEl></value></entry><entry><key>HTTP Context Map</key><value><allowableValues><displayName>StandardHttpContextMap</displayName><value>bc09bb31-fbf8-44ef-8115-0351fe2e4e37</value></allowableValues><description>The HTTP Context Map Controller Service to use for caching the HTTP Request Information</description><displayName>HTTP Context Map</displayName><dynamic>false</dynamic><identifiesControllerService>org.apache.nifi.http.HttpContextMap</identifiesControllerService><name>HTTP Context Map</name><required>true</required><sensitive>false</sensitive><supportsEl>false</supportsEl></value></entry><entry><key>Allowed Paths</key><value><description>A Regular Expression that specifies the valid HTTP Paths that are allowed in the incoming URL Requests. If this value is specified and the path of the HTTP Requests does not match this Regular Expression, the Processor will respond with a 404: NotFound</description><displayName>Allowed Paths</displayName><dynamic>false</dynamic><name>Allowed Paths</name><required>false</required><sensitive>false</sensitive><supportsEl>false</supportsEl></value></entry><entry><key>Default URL Character Set</key><value><defaultValue>UTF-8</defaultValue><description>The character set to use for decoding URL parameters if the HTTP Request does not supply one</description><displayName>Default URL Character Set</displayName><dynamic>false</dynamic><name>Default URL Character Set</name><required>true</required><sensitive>false</sensitive><supportsEl>false</supportsEl></value></entry><entry><key>Allow GET</key><value><allowableValues><displayName>true</displayName><value>true</value></allowableValues><allowableValues><displayName>false</displayName><value>false</value></allowableValues><defaultValue>true</defaultValue><description>Allow HTTP GET Method</description><displayName>Allow GET</displayName><dynamic>false</dynamic><name>Allow GET</name><required>true</required><sensitive>false</sensitive><supportsEl>false</supportsEl></value></entry><entry><key>Allow POST</key><value><allowableValues><displayName>true</displayName><value>true</value></allowableValues><allowableValues><displayName>false</displayName><value>false</value></allowableValues><defaultValue>true</defaultValue><description>Allow HTTP POST Method</description><displayName>Allow POST</displayName><dynamic>false</dynamic><name>Allow POST</name><required>true</required><sensitive>false</sensitive><supportsEl>false</supportsEl></value></entry><entry><key>Allow PUT</key><value><allowableValues><displayName>true</displayName><value>true</value></allowableValues><allowableValues><displayName>false</displayName><value>false</value></allowableValues><defaultValue>true</defaultValue><description>Allow HTTP PUT Method</description><displayName>Allow PUT</displayName><dynamic>false</dynamic><name>Allow PUT</name><required>true</required><sensitive>false</sensitive><supportsEl>false</supportsEl></value></entry><entry><key>Allow DELETE</key><value><allowableValues><displayName>true</displayName><value>true</value></allowableValues><allowableValues><displayName>false</displayName><value>false</value></allowableValues><defaultValue>true</defaultValue><description>Allow HTTP DELETE Method</description><displayName>Allow DELETE</displayName><dynamic>false</dynamic><name>Allow DELETE</name><required>true</required><sensitive>false</sensitive><supportsEl>false</supportsEl></value></entry><entry><key>Allow HEAD</key><value><allowableValues><displayName>true</displayName><value>true</value></allowableValues><allowableValues><displayName>false</displayName><value>false</value></allowableValues><defaultValue>false</defaultValue><description>Allow HTTP HEAD Method</description><displayName>Allow HEAD</displayName><dynamic>false</dynamic><name>Allow HEAD</name><required>true</required><sensitive>false</sensitive><supportsEl>false</supportsEl></value></entry><entry><key>Allow OPTIONS</key><value><allowableValues><displayName>true</displayName><value>true</value></allowableValues><allowableValues><displayName>false</displayName><value>false</value></allowableValues><defaultValue>false</defaultValue><description>Allow HTTP OPTIONS Method</description><displayName>Allow OPTIONS</displayName><dynamic>false</dynamic><name>Allow OPTIONS</name><required>true</required><sensitive>false</sensitive><supportsEl>false</supportsEl></value></entry><entry><key>Additional HTTP Methods</key><value><description>A comma-separated list of non-standard HTTP Methods that should be allowed</description><displayName>Additional HTTP Methods</displayName><dynamic>false</dynamic><name>Additional HTTP Methods</name><required>false</required><sensitive>false</sensitive><supportsEl>false</supportsEl></value></entry><entry><key>Client Authentication</key><value><allowableValues><description>Processor will not authenticate clients. Anyone can communicate with this Processor anonymously</description><displayName>No Authentication</displayName><value>No Authentication</value></allowableValues><allowableValues><description>Processor will try to verify the client but if unable to verify will allow the client to communicate anonymously</description><displayName>Want Authentication</displayName><value>Want Authentication</value></allowableValues><allowableValues><description>Processor will reject communications from any client unless the client provides a certificate that is trusted by the TrustStorespecified in the SSL Context Service</description><displayName>Need Authentication</displayName><value>Need Authentication</value></allowableValues><defaultValue>No Authentication</defaultValue><description>Specifies whether or not the Processor should authenticate clients. This value is ignored if the &lt;SSL Context Service&gt; Property is not specified or the SSL Context provided uses only a KeyStore and not a TrustStore.</description><displayName>Client Authentication</displayName><dynamic>false</dynamic><name>Client Authentication</name><required>true</required><sensitive>false</sensitive><supportsEl>false</supportsEl></value></entry></descriptors><lossTolerant>false</lossTolerant><penaltyDuration>30 sec</penaltyDuration><properties><entry><key>Listening Port</key><value>8680</value></entry><entry><key>Hostname</key><value>localhost</value></entry><entry><key>SSL Context Service</key></entry><entry><key>HTTP Context Map</key><value>bc09bb31-fbf8-44ef-8115-0351fe2e4e37</value></entry><entry><key>Allowed Paths</key></entry><entry><key>Default URL Character Set</key></entry><entry><key>Allow GET</key></entry><entry><key>Allow POST</key></entry><entry><key>Allow PUT</key></entry><entry><key>Allow DELETE</key></entry><entry><key>Allow HEAD</key></entry><entry><key>Allow OPTIONS</key></entry><entry><key>Additional HTTP Methods</key></entry><entry><key>Client Authentication</key></entry></properties><runDurationMillis>0</runDurationMillis><schedulingPeriod>0 sec</schedulingPeriod><schedulingStrategy>TIMER_DRIVEN</schedulingStrategy><yieldDuration>1 sec</yieldDuration></config><name>Incoming Ambari report</name><relationships><autoTerminate>false</autoTerminate><description>All content that is received is routed to the 'success' relationship</description><name>success</name></relationships><state>STOPPED</state><style/><supportsEventDriven>false</supportsEventDriven><supportsParallelProcessing>true</supportsParallelProcessing><type>org.apache.nifi.processors.standard.HandleHttpRequest</type></processors><processors><id>c5a94d4c-c2bb-40de-a827-244e74528fe4</id><parentGroupId>b8cbae40-4019-4c69-b185-df812e88e5be</parentGroupId><position><x>375.19744400406313</x><y>101.97166752234247</y></position><config><bulletinLevel>WARN</bulletinLevel><comments></comments><concurrentlySchedulableTaskCount>1</concurrentlySchedulableTaskCount><defaultConcurrentTasks><entry><key>TIMER_DRIVEN</key><value>1</value></entry><entry><key>EVENT_DRIVEN</key><value>0</value></entry><entry><key>CRON_DRIVEN</key><value>1</value></entry></defaultConcurrentTasks><defaultSchedulingPeriod><entry><key>TIMER_DRIVEN</key><value>0 sec</value></entry><entry><key>CRON_DRIVEN</key><value>* * * * * ?</value></entry></defaultSchedulingPeriod><descriptors><entry><key>HTTP Status Code</key><value><description>The HTTP Status Code to use when responding to the HTTP Request. See Section 10 of RFC 2616 for more information.</description><displayName>HTTP Status Code</displayName><dynamic>false</dynamic><name>HTTP Status Code</name><required>true</required><sensitive>false</sensitive><supportsEl>true</supportsEl></value></entry><entry><key>HTTP Context Map</key><value><allowableValues><displayName>StandardHttpContextMap</displayName><value>bc09bb31-fbf8-44ef-8115-0351fe2e4e37</value></allowableValues><description>The HTTP Context Map Controller Service to use for caching the HTTP Request Information</description><displayName>HTTP Context Map</displayName><dynamic>false</dynamic><identifiesControllerService>org.apache.nifi.http.HttpContextMap</identifiesControllerService><name>HTTP Context Map</name><required>true</required><sensitive>false</sensitive><supportsEl>false</supportsEl></value></entry></descriptors><lossTolerant>false</lossTolerant><penaltyDuration>30 sec</penaltyDuration><properties><entry><key>HTTP Status Code</key><value>200</value></entry><entry><key>HTTP Context Map</key><value>bc09bb31-fbf8-44ef-8115-0351fe2e4e37</value></entry></properties><runDurationMillis>0</runDurationMillis><schedulingPeriod>0 sec</schedulingPeriod><schedulingStrategy>TIMER_DRIVEN</schedulingStrategy><yieldDuration>1 sec</yieldDuration></config><name>Respond OK</name><relationships><autoTerminate>true</autoTerminate><description>FlowFiles will be routed to this Relationship if the Processor is unable to respond to the requestor. This may happen, for instance, if the connection times out or if NiFi is restarted before responding to the HTTP Request.</description><name>failure</name></relationships><relationships><autoTerminate>true</autoTerminate><description>FlowFiles will be routed to this Relationship after the response has been successfully sent to the requestor</description><name>success</name></relationships><state>STOPPED</state><style/><supportsEventDriven>false</supportsEventDriven><supportsParallelProcessing>true</supportsParallelProcessing><type>org.apache.nifi.processors.standard.HandleHttpResponse</type></processors></snippet><timestamp>01/06/2016 14:14:44 EST</timestamp></template>